{
	"events": [
	    { 
	    	"startDate": "08-10-2014", 
	    	"endDate": "08-13-2014", 
	    	"title": "Hey!Stac",
	    	"shortTitle": "HS",
	    	"description": "Talking design, business and tech.",
	    	"location": "11 - 15 Hunslet Road, Leeds, West Yorkshire, LS10 1JQ",
	    	"brandingAccent": "#fe6f53"
	    },
	    { 
	    	"startDate": "08-21-2014", 
	    	"endDate": "08-23-2014", 
	    	"title": "NUX Leeds", 
	    	"shortTitle": "NUX",
	    	"description": "Yorkshire Digital Conference",
	    	"location": "11 - 15 Hunslet Road, Leeds, West Yorkshire, LS10 1JQ",
	    	"brandingAccent": "#1AAA2B"
	    },
	    { 
	    	"startDate": "08-8-2014", 
	    	"endDate": "08-8-2014", 
	    	"title": "Leeds Data Thing", 
	    	"shortTitle": "LDT",
	    	"description": "Yorkshire Digital Conference",
	    	"location": "11 - 15 Hunslet Road, Leeds, West Yorkshire, LS10 1JQ",
	    	"brandingAccent": "#cd007b"
	    },
	    { 
	    	"startDate": "08-08-2014", 
	    	"endDate": "08-08-2014", 
	    	"title": "NUX Leeds", 
	    	"shortTitle": "NUX",
	    	"description": "Yorkshire Digital Conference",
	    	"location": "11 - 15 Hunslet Road, Leeds, West Yorkshire, LS10 1JQ",
	    	"brandingAccent": "#1AAA2B"
	    }
	  ]
}